LICENSE.txt
MANIFEST.in
README.md
setup.cfg
setup.py
django_pq/__init__.py
django_pq/cache.py
django_pq/fixups.py
django_pq/lazy.py
django_pq/queryset.py
django_prepared_queries.egg-info/PKG-INFO
django_prepared_queries.egg-info/SOURCES.txt
django_prepared_queries.egg-info/dependency_links.txt
django_prepared_queries.egg-info/requires.txt
django_prepared_queries.egg-info/top_level.txt