Metadata-Version: 1.0
Name: django-prepared-queries
Version: 0.2.1
Summary: Caches SQL queries built with Django ORM
Home-page: https://github.com/rutube/django_prepared_queries
Author: Tumbler
Author-email: zimbler@bk.ru
License: Beer license
Platform: UNKNOWN
